mic_worker/__init__.py
mic_worker/typed.py
mic_worker/worker.py
mic_worker-0.1.2.dist-info/licenses/LICENCE.md
mic_worker-0.1.2.dist-info/METADATA
mic_worker-0.1.2.dist-info/WHEEL
mic_worker-0.1.2.dist-info/top_level.txt
mic_worker-0.1.2.dist-info/RECORD
