Metadata-Version: 2.4
Name: mic-worker
Version: 0.1.2
Summary: Worker package for async tasks
Project-URL: Repository, https://github.com/titigmr/async-api
Project-URL: Documentation, https://github.com/titigmr/async-api/workers/python/README.md
Requires-Python: >=3.13
License-File: LICENCE.md
Requires-Dist: aio-pika>=9.5.5
Requires-Dist: pytest>=8.4.2
Provides-Extra: test
Requires-Dist: pytest>=7.0.0; extra == "test"
Requires-Dist: pytest-asyncio>=0.21.0; extra == "test"
Requires-Dist: pytest-mock>=3.10.0; extra == "test"
Dynamic: license-file
